MANIFEST.in
README.md
little_pger.py
setup.cfg
setup.py
little_pger.egg-info/PKG-INFO
little_pger.egg-info/SOURCES.txt
little_pger.egg-info/dependency_links.txt
little_pger.egg-info/requires.txt
little_pger.egg-info/top_level.txt